conferencetimer/Remote.py
conferencetimer/Timer.py
conferencetimer/__init__.py
conferencetimer-1.0.9.dist-info/licenses/LICENSE
conferencetimer-1.0.9.dist-info/METADATA
conferencetimer-1.0.9.dist-info/WHEEL
conferencetimer-1.0.9.dist-info/entry_points.txt
conferencetimer-1.0.9.dist-info/top_level.txt
conferencetimer-1.0.9.dist-info/RECORD
