Metadata-Version: 2.4
Name: conferencetimer
Version: 1.0.9
Summary: PyQt6 based timer and remote application for conference talks
Author-email: Luis Bonah <bonah@ph1.uni-koeln.de>
Keywords: Conference,Timer,PyQt6
Classifier: Programming Language :: Python :: 3
Classifier: License :: OSI Approved :: GNU General Public License v3 (GPLv3)
Classifier: Operating System :: OS Independent
Requires-Python: >=3.7
License-File: LICENSE
Requires-Dist: numpy
Requires-Dist: PyQt6
Dynamic: license-file
